airbnb_host_api/__init__.py
airbnb_host_api/airbnb.py
airbnb_host_api/airbnb_locators.py
airbnb_host_api/base.py
airbnb_host_api-0.0.3.dist-info/METADATA
airbnb_host_api-0.0.3.dist-info/WHEEL
airbnb_host_api-0.0.3.dist-info/licenses/LICENSE
airbnb_host_api-0.0.3.dist-info/RECORD
