Metadata-Version: 2.4
Name: airbnb-host-api
Version: 0.0.3
Summary: Simple native Airbnb API wrapper
Author-email: kaxcheg <kaxcheg@gmail.com>
License: MIT License
License-File: LICENSE
Keywords: API,airbnb
Classifier: Operating System :: OS Independent
Classifier: Programming Language :: Python :: 3
Requires-Python: >=3.12.5
Requires-Dist: requests>=2.32.3
Requires-Dist: selenium>=4.25
